Metadata-Version: 1.0
Name: cloudshell-networking-juniper-junos
Version: 3.0.150
Summary: QualiSystems Juniper JUNOS package
Home-page: http://www.qualisystems.com/
Author: QualiSystems
Author-email: info@qualisystems.com
License: UNKNOWN
Platform: UNKNOWN
